odoo/addons/ssi_web_clear_all_filter/README.rst
odoo/addons/ssi_web_clear_all_filter/__init__.py
odoo/addons/ssi_web_clear_all_filter/__manifest__.py
odoo/addons/ssi_web_clear_all_filter/static/description/icon.png
odoo/addons/ssi_web_clear_all_filter/static/src/js/clear_all_filter.js
odoo/addons/ssi_web_clear_all_filter/static/src/scss/clear_all_filter.scss
odoo/addons/ssi_web_clear_all_filter/static/src/xml/clear_all_filter.xml
odoo/addons/ssi_web_clear_all_filter/templates/assets.xml
odoo14_addon_ssi_web_clear_all_filter-14.0.1.0.0.dist-info/METADATA
odoo14_addon_ssi_web_clear_all_filter-14.0.1.0.0.dist-info/WHEEL
odoo14_addon_ssi_web_clear_all_filter-14.0.1.0.0.dist-info/top_level.txt
odoo14_addon_ssi_web_clear_all_filter-14.0.1.0.0.dist-info/RECORD
